{
  "tree": [
    {
      "slug": "home",
      "name": "Documentation"
    },
    {
      "slug": "getting-started",
      "name": "Start with Retrobox"
    },
    {
      "slug": "tools",
      "name": "Tools"
    },
    {
      "slug": "assembly",
      "name": "Assembly"
    },
    {
      "slug": "finishing",
      "name": "Finishing"
    },
    {
      "type": "page",
      "slug": "installation",
      "name": "Installation"
    },
    {
      "slug": "questions",
      "name": "Questions"
    },
    {
      "slug": "troubleshooting",
      "name": "Troubleshooting"
    },
    {
      "slug": "manual-installation",
      "name": "Manual installation"
    },
    {
      "slug": "technical-specification",
      "name": "Technical specification"
    }
  ]
}
